pysite/__init__.py
pysite/__main__.py
pysite/tags.py
pysite/pyx/__init__.py
pysite/pyx/generator.py
pysite/pyx/pyxc.py
pysite/pyx/xmlparser.py
pyx_pysite-1.0.3.dist-info/LICENSE
pyx_pysite-1.0.3.dist-info/METADATA
pyx_pysite-1.0.3.dist-info/WHEEL
pyx_pysite-1.0.3.dist-info/entry_points.txt
pyx_pysite-1.0.3.dist-info/top_level.txt
pyx_pysite-1.0.3.dist-info/RECORD
