Metadata-Version: 2.1
Name: pyx-pysite
Version: 1.0.3
Summary: Pysite is a Python web framework, inspired by JSX. It uses Flask in the backend. Common commands for the `pysite` CLI are `new <projectname>` and `run`.
Author-email: Carl Furtado <carlzfurtado@gmail.com>
License: The MIT License (MIT)
Project-URL: Home, https://github.com/User0332/pyx
Classifier: License :: OSI Approved :: MIT License
Classifier: Intended Audience :: Developers
Classifier: Programming Language :: Python
Classifier: Programming Language :: Python :: 3
Classifier: Topic :: Text Processing :: Markup :: HTML
Classifier: Operating System :: OS Independent
License-File: LICENSE
Requires-Dist: flask (>=2.3.0)
